xlsxwriter/__init__.py
xlsxwriter/app.py
xlsxwriter/chart.py
xlsxwriter/chart_area.py
xlsxwriter/chart_bar.py
xlsxwriter/chart_column.py
xlsxwriter/chart_doughnut.py
xlsxwriter/chart_line.py
xlsxwriter/chart_pie.py
xlsxwriter/chart_radar.py
xlsxwriter/chart_scatter.py
xlsxwriter/chart_stock.py
xlsxwriter/chartsheet.py
xlsxwriter/color.py
xlsxwriter/comments.py
xlsxwriter/contenttypes.py
xlsxwriter/core.py
xlsxwriter/custom.py
xlsxwriter/drawing.py
xlsxwriter/exceptions.py
xlsxwriter/feature_property_bag.py
xlsxwriter/format.py
xlsxwriter/image.py
xlsxwriter/metadata.py
xlsxwriter/packager.py
xlsxwriter/relationships.py
xlsxwriter/rich_value.py
xlsxwriter/rich_value_rel.py
xlsxwriter/rich_value_structure.py
xlsxwriter/rich_value_types.py
xlsxwriter/shape.py
xlsxwriter/sharedstrings.py
xlsxwriter/styles.py
xlsxwriter/table.py
xlsxwriter/theme.py
xlsxwriter/url.py
xlsxwriter/utility.py
xlsxwriter/vml.py
xlsxwriter/workbook.py
xlsxwriter/worksheet.py
xlsxwriter/xmlwriter.py
xlsxwriter-3.2.4.data/scripts/vba_extract.py
xlsxwriter-3.2.4.dist-info/LICENSE.txt
xlsxwriter-3.2.4.dist-info/METADATA
xlsxwriter-3.2.4.dist-info/WHEEL
xlsxwriter-3.2.4.dist-info/top_level.txt
xlsxwriter-3.2.4.dist-info/RECORD
